ts_type/__init__.py
ts_type/builders.py
ts_type/exceptions.py
ts_type/generators.py
ts_type/nodes.py
ts_type/py.typed
ts_type/utils.py
ts_type/version.py
ts_type-0.3.4.dist-info/licenses/LICENSE
ts_type-0.3.4.dist-info/METADATA
ts_type-0.3.4.dist-info/WHEEL
ts_type-0.3.4.dist-info/top_level.txt
ts_type-0.3.4.dist-info/RECORD
