Metadata-Version: 2.4
Name: ts_type
Version: 0.3.4
Summary: ts_type generates typescript's type from python code
Home-page: https://github.com/saryou/ts_type
Author: Ryosuke Sasaki
Author-email: saryou.ssk@gmail.com
Project-URL: Bug Tracker, https://github.com/saryou/ts_type/issues
Classifier: Programming Language :: Python :: 3
Classifier: License :: OSI Approved :: MIT License
Classifier: Operating System :: OS Independent
Requires-Python: >=3.9
License-File: LICENSE
Dynamic: author
Dynamic: author-email
Dynamic: classifier
Dynamic: description
Dynamic: description-content-type
Dynamic: home-page
Dynamic: license-file
Dynamic: project-url
Dynamic: requires-python
Dynamic: summary
